django_enum/__init__.py
django_enum/choices.py
django_enum/drf.py
django_enum/fields.py
django_enum/filters.py
django_enum/forms.py
django_enum/py.typed
django_enum/query.py
django_enum/urls.py
django_enum/utils.py
django_enum-2.2.5.dist-info/METADATA
django_enum-2.2.5.dist-info/WHEEL
django_enum-2.2.5.dist-info/licenses/LICENSE
django_enum-2.2.5.dist-info/RECORD
