Metadata-Version: 2.4
Name: django-enum
Version: 2.2.5
Summary: Full and natural support for enumerations as Django model fields.
Project-URL: Homepage, https://django-enum.readthedocs.io
Project-URL: Documentation, https://django-enum.readthedocs.io
Project-URL: Repository, https://github.com/django-commons/django-enum
Project-URL: Issues, https://github.com/django-commons/django-enum/issues
Project-URL: Changelog, https://django-enum.readthedocs.io/en/latest/changelog.html
Project-URL: Code_of_Conduct, https://github.com/django-commons/django-enum/blob/main/CODE_OF_CONDUCT.md
Author-email: Brian Kohan <bckohan@gmail.com>
License-Expression: MIT
License-File: LICENSE
Keywords: bitfield,bitmask,database,defines,django,enum,field,flags,mask,properties
Classifier: Development Status :: 5 - Production/Stable
Classifier: Environment :: Console
Classifier: Framework :: Django
Classifier: Framework :: Django :: 3.2
Classifier: Framework :: Django :: 4.0
Classifier: Framework :: Django :: 4.1
Classifier: Framework :: Django :: 4.2
Classifier: Framework :: Django :: 5.0
Classifier: Framework :: Django :: 5.1
Classifier: Framework :: Django :: 5.2
Classifier: Framework :: Django :: 6.0
Classifier: Intended Audience :: Developers
Classifier: License :: OSI Approved :: MIT License
Classifier: Natural Language :: English
Classifier: Operating System :: OS Independent
Classifier: Programming Language :: Python
Classifier: Programming Language :: Python :: 3.9
Classifier: Programming Language :: Python :: 3.10
Classifier: Programming Language :: Python :: 3.11
Classifier: Programming Language :: Python :: 3.12
Classifier: Programming Language :: Python :: 3.13
Classifier: Programming Language :: Python :: 3.14
Classifier: Topic :: Internet :: WWW/HTTP
Classifier: Topic :: Internet :: WWW/HTTP :: Site Management
Classifier: Topic :: Software Development :: Libraries
Classifier: Topic :: Software Development :: Libraries :: Python Modules
Requires-Python: <4.0,>=3.9
Requires-Dist: django<6.1,>=3.2
Provides-Extra: filters
Requires-Dist: django-filter>=21; extra == 'filters'
Provides-Extra: properties
Requires-Dist: enum-properties>=2.3.0; (python_version < '3.14') and extra == 'properties'
Requires-Dist: enum-properties>=2.4.0; (python_version >= '3.14') and extra == 'properties'
Provides-Extra: rest
Requires-Dist: djangorestframework<4.0,>=3.9; extra == 'rest'
